{
  "slug": "mallorca-confidencial-en-catala",
  "title": "Mallorca Confidencial",
  "href": "https://webcinema.cat/pellicula/mallorca-confidencial-en-catala",
  "sessionCount": 1,
  "cinemaCount": 1,
  "municipiCount": 1,
  "sessions": [
    {
      "id": "269691b101c99d28",
      "filmSlug": "mallorca-confidencial-en-catala",
      "filmTitle": "Mallorca Confidencial",
      "cinemaSlug": "cinemes-texas",
      "cinemaName": "Cinemes Texas",
      "municipiSlug": "barcelona",
      "municipiName": "Barcelona",
      "sessionDate": "2026-07-03",
      "sessionTime": "16:00",
      "languageLabel": "VO en català",
      "bookingUrl": "https://espaitexas.koobin.cat/ca/mallorca-confidencial-vo-20260703-1600",
      "pickerUrl": "https://espaitexas.koobin.cat/ca/mallorca-confidencial-vo-20260703-1600",
      "sourceUrl": "https://espaitexas.cat",
      "extractorType": "html-static",
      "capturedAt": "2026-07-03T05:30:04Z"
    }
  ]
}
