{
  "slug": "figueres",
  "name": "Figueres",
  "href": "https://webcinema.cat/municipi/figueres/cinema-en-catala",
  "sessionCount": 2,
  "filmCount": 2,
  "cinemaCount": 1,
  "sessions": [
    {
      "id": "698552e220bc20b3",
      "filmSlug": "viatge-al-pais-dels-blancs-en-catala",
      "filmTitle": "Viatge al país dels blancs",
      "cinemaSlug": "cat-cines",
      "cinemaName": "CAT Cines",
      "municipiSlug": "figueres",
      "municipiName": "Figueres",
      "sessionDate": "2026-07-02",
      "sessionTime": "22:00",
      "languageLabel": "Català",
      "bookingUrl": "https://www.catcines.cat//film-4750/p?cat-viatge-al-pais-dels-blanc",
      "pickerUrl": "https://www.catcines.cat//film-4750/p?cat-viatge-al-pais-dels-blanc",
      "sourceUrl": "https://www.catcines.cat//film-4750/p?cat-viatge-al-pais-dels-blanc",
      "extractorType": "catcines-html",
      "capturedAt": "2026-07-02T21:23:33Z"
    },
    {
      "id": "14ebb2840f73201d",
      "filmSlug": "viva-en-catala",
      "filmTitle": "Viva",
      "cinemaSlug": "cat-cines",
      "cinemaName": "CAT Cines",
      "municipiSlug": "figueres",
      "municipiName": "Figueres",
      "sessionDate": "2026-07-02",
      "sessionTime": "22:00",
      "languageLabel": "Català",
      "bookingUrl": "https://www.catcines.cat//film-4749/p?cat-viva",
      "pickerUrl": "https://www.catcines.cat//film-4749/p?cat-viva",
      "sourceUrl": "https://www.catcines.cat//film-4749/p?cat-viva",
      "extractorType": "catcines-html",
      "capturedAt": "2026-07-02T21:23:35Z"
    }
  ]
}
